simgadom.cpython-311-i386-linux-musl.so
simgadom-0.0.1.dist-info/WHEEL
simgadom-0.0.1.dist-info/top_level.txt
simgadom-0.0.1.dist-info/RECORD
simgadom-0.0.1.dist-info/METADATA
simgadom.libs/libstdc++-d2a021ba.so.6.0.32
simgadom.libs/libgcc_s-f3fb5a36.so.1
