Metadata-Version: 2.1
Name: simgadom
Version: 0.0.1
Summary: pybind11 extension
Author: Dmitry Lednov
Author-email: lednov.d.a@sberbank.ru
Requires: pybind11
